p3gpt/__init__.py
p3gpt/handlers/__init__.py
p3gpt/handlers/p3_multimodal.py
p3gpt/handlers/p3_multimodal_handler.py
p3gpt/mpt_7b/__init__.py
p3gpt/mpt_7b/adapt_tokenizer.py
p3gpt/mpt_7b/attention.py
p3gpt/mpt_7b/blocks.py
p3gpt/mpt_7b/configuration_mpt.py
p3gpt/mpt_7b/custom_embedding.py
p3gpt/mpt_7b/fc.py
p3gpt/mpt_7b/ffn.py
p3gpt/mpt_7b/flash_attn_triton.py
p3gpt/mpt_7b/hf_prefixlm_converter.py
p3gpt/mpt_7b/meta_init_context.py
p3gpt/mpt_7b/modeling_mpt.py
p3gpt/mpt_7b/norm.py
p3gpt/mpt_7b/param_init_fns.py
p3gpt/mpt_7b/requirements.txt
p3gpt/mpt_7b/warnings.py
p3gpt/p3screen/__init__.py
p3gpt/p3screen/screening.py
p3gpt-0.1.0.dist-info/LICENCE
p3gpt-0.1.0.dist-info/METADATA
p3gpt-0.1.0.dist-info/WHEEL
p3gpt-0.1.0.dist-info/top_level.txt
p3gpt-0.1.0.dist-info/RECORD
